autoextract/__init__.py
autoextract/__main__.py
autoextract/__version__.py
autoextract/apikey.py
autoextract/batching.py
autoextract/constants.py
autoextract/request.py
autoextract/stats.py
autoextract/sync.py
autoextract/utils.py
autoextract/aio/__init__.py
autoextract/aio/client.py
autoextract/aio/errors.py
autoextract/aio/retry.py
scrapinghub_autoextract-0.6.1.dist-info/LICENSE
scrapinghub_autoextract-0.6.1.dist-info/METADATA
scrapinghub_autoextract-0.6.1.dist-info/WHEEL
scrapinghub_autoextract-0.6.1.dist-info/top_level.txt
scrapinghub_autoextract-0.6.1.dist-info/RECORD
